{"lastUsed":1667205514729,"path":"C:\/Java_Swing","projectCount":1,"recentFiles":[{"path":"\/Project\/src\/search2","parentWorkspace":"C:\/Java_Swing","name":"MemberDAO.java","lastModified":1667201103590,"locationURI":"file:\/C:\/Java_Swing\/Project\/src\/search2\/MemberDAO.java"},{"path":"\/Project\/src\/search","parentWorkspace":"C:\/Java_Swing","name":"UserDefaultJTableDAO.java","lastModified":1666858115742,"locationURI":"file:\/C:\/Java_Swing\/Project\/src\/search\/UserDefaultJTableDAO.java"},{"path":"\/Project\/src\/mainView","parentWorkspace":"C:\/Java_Swing","name":"ViewerMain.java","lastModified":1666946663021,"locationURI":"file:\/C:\/Java_Swing\/Project\/src\/mainView\/ViewerMain.java"},{"path":"\/Project\/src\/search2","parentWorkspace":"C:\/Java_Swing","name":"MemberVO.java","lastModified":1667194993840,"locationURI":"file:\/C:\/Java_Swing\/Project\/src\/search2\/MemberVO.java"},{"path":"\/Project\/src\/search","parentWorkspace":"C:\/Java_Swing","name":"MenuJTabaleExam.java","lastModified":1667203491950,"locationURI":"file:\/C:\/Java_Swing\/Project\/src\/search\/MenuJTabaleExam.java"},{"path":"\/Project\/src\/search2","parentWorkspace":"C:\/Java_Swing","name":"Membergui.java","lastModified":1667205016606,"locationURI":"file:\/C:\/Java_Swing\/Project\/src\/search2\/Membergui.java"},{"path":"\/Project\/src\/login","parentWorkspace":"\/Users\/shinchanghyeok\/Desktop\/4학년_2학기\/멀티캠퍼스\/Java_Swing","name":"Login.java","lastModified":1666768143189,"locationURI":"file:\/Users\/shinchanghyeok\/Desktop\/4학년_2학기\/멀티캠퍼스\/Java_Swing\/Project\/src\/login\/Login.java"},{"path":"\/Project\/src\/search2","parentWorkspace":"C:\/Java_Swing","name":"Membergui2.java","lastModified":1667205514753,"locationURI":"file:\/C:\/Java_Swing\/Project\/src\/search2\/Membergui2.java"},{"path":"\/Project\/src\/search","parentWorkspace":"C:\/Java_Swing","name":"UserJDailogGUI.java","lastModified":1666858115742,"locationURI":"file:\/C:\/Java_Swing\/Project\/src\/search\/UserJDailogGUI.java"}]}